README.rst
setup.py
ognom/__init__.py
ognom/_registry.py
ognom/base.py
ognom/collection.py
ognom/connection.py
ognom/document.py
ognom/fields.py
ognom/validators.py
ognom.egg-info/PKG-INFO
ognom.egg-info/SOURCES.txt
ognom.egg-info/dependency_links.txt
ognom.egg-info/requires.txt
ognom.egg-info/top_level.txt
ognom/helpers/__init__.py
ognom/helpers/counter.py
ognom/helpers/lifecycle.py
tests/__init__.py
tests/common.py
tests/conftest.py
tests/test_mongo.py
tests/helpers/__init__.py
tests/helpers/test_counter.py
tests/helpers/test_lifecycle.py
tests/test_fields/__init__.py
tests/test_fields/test_document_field.py
tests/test_fields/test_fields.py