Metadata-Version: 1.1
Name: ognom
Version: 0.5.4
Summary: Neat ODM wrapper around great PyMongo driver
Home-page: https://github.com/lorehov/ognom
Author: Lev Orekhov
Author-email: lev.orekhov@gmail.com
License: MIT
Keywords: mongo mongodb pymongo orm odm
Platform: UNKNOWN
Classifier: Development Status :: 5 - Production/Stable
Classifier: License :: OSI Approved :: MIT License
Classifier: Natural Language :: English
Classifier: Operating System :: OS Independent
Classifier: Programming Language :: Python :: 2.7
Classifier: Programming Language :: Python :: 3.3
Classifier: Programming Language :: Python :: 3.4
Classifier: Programming Language :: Python :: Implementation :: PyPy
Classifier: Topic :: Software Development :: Libraries :: Python Modules
